README.md
setup.cfg
setup.py
OSMPythonTools/__info__.py
OSMPythonTools/__init__.py
OSMPythonTools/api.py
OSMPythonTools/data.py
OSMPythonTools/element.py
OSMPythonTools/nominatim.py
OSMPythonTools/overpass.py
OSMPythonTools.egg-info/PKG-INFO
OSMPythonTools.egg-info/SOURCES.txt
OSMPythonTools.egg-info/dependency_links.txt
OSMPythonTools.egg-info/requires.txt
OSMPythonTools.egg-info/top_level.txt
OSMPythonTools/internal/__init__.py
OSMPythonTools/internal/cacheObject.py
OSMPythonTools/internal/elementShallow.py
OSMPythonTools/internal/singletonApi.py