Metadata-Version: 1.1
Name: OSMPythonTools
Version: 0.3.2
Summary: A library to access OpenStreetMap related services
Home-page: https://github.com/mocnik-science/osm-python-tools
Author: Franz-Benjamin Mocnik
Author-email: mail@mocnik-science.net
License: GPL-3
Keywords: OpenStreetMap,OSM,service,overpass,nominatim
Platform: UNKNOWN
Classifier: Development Status :: 4 - Beta
Classifier: Programming Language :: Python :: 3
